{
	"plan_de_estudio":
	{
		"nombre": "Ingeniería en Sistemas",
		"semestres":
		{
			"Semestre 1": 
			[
				{
					"nombre": "Programación 1",
					"codigo": "1054",
					"creditos": 4
				},
				{
					"nombre": "Cálculo 10",
					"codigo": "1004",
					"creditos": 6
				},
				{
					"nombre": "Sistemas de Representación 10",
					"codigo": "1006",
					"creditos": 4
				},
				{
					"nombre": "Ingeniería de Sistemas",
					"codigo": "1053",
					"creditos": 4
				}
			],
			"Semestre 2": 
			[
				{
					"nombre": "Programación 2",
					"codigo": "1055",
					"creditos": 4
				},
				{
					"nombre": "Cálculo 20",
					"codigo": "1012",
					"creditos": 6
				},
				{
					"nombre": "Física 11",
					"codigo": "1011",
					"creditos": 5
				},
				{
					"nombre": "Introducción a los Procesos Químicos",
					"codigo": "1056",
					"creditos": 5
				}
			],
			"Semestre 3": 
			[
				{
					"nombre": "Arquitectura de Computadoras",
					"codigo": "1057",
					"creditos": 4
				},
				{
					"nombre": "Cálculo 30",
					"codigo": "1018",
					"creditos": 6
				},
				{
					"nombre": "Física 21",
					"codigo": "1017",
					"creditos": 5
				},
				{
					"nombre": "Mecánica Racional",
					"codigo": "1052",
					"creditos": 4
				},
				{
					"nombre": "Inglés I",
					"codigo": "1039",
					"creditos": 3
				}
			]
		} 
	}
}
